{"kpi":"faenapecuaria","t":"Faena Pecuaria","st":"En Cabezas","sd":"","c":"<p>El indicador de Producción de Petróleo en Argentina se refiere a la cantidad total de petróleo crudo producido en el país en un período determinado, medido en millones de metros cúbicos (m3). La producción de petróleo es uno de los indicadores clave de la economía argentina, ya que el país tiene una importante industria petrolera que es una fuente importante de ingresos y empleo.</p><p>La producción de petróleo en Argentina ha experimentado altibajos en las últimas décadas, con períodos de crecimiento y de declive. En general, la producción de petróleo se ha visto afectada por una serie de factores, como los precios del petróleo, las inversiones en la industria, la exploración de nuevas reservas y los avances tecnológicos.</p><p>El pico de producción de petróleo en Argentina se alcanzó en la década de 1990, cuando se producían más de 1.000 millones de metros cúbicos de petróleo crudo al año. Sin embargo, la producción ha disminuido desde entonces, alcanzando su nivel más bajo en 2017, cuando se produjeron alrededor de 470 millones de metros cúbicos. Desde entonces, la producción ha mostrado cierta recuperación, alcanzando los 554 millones de metros cúbicos en 2019.</p><p>Es importante destacar que la producción de petróleo de Argentina se concentra en las cuencas del golfo San Jorge, Neuquina y Cuyana, que representan la mayor parte de la producción de petróleo del país. También hay una producción menor en las cuencas del Chaco, Austral y Colorado.</p>","fd":"datos.gob.ar","fdr":"https://datos.gob.ar/it/dataset/sspm-produccion-ventas-petroleo-derivados/archivo/sspm_363.3","fu":"MECON","fur":"https://www.argentina.gob.ar/economia/politicaeconomica/macroeconomica","frec":"Mensual","fruc":"mean","u":"2023-04-17","d":"El Estimador mensual de actividad económica (EMAE) refleja la evolución mensual de la actividad económica del conjunto de los sectores productivos a nivel nacional. Este indicador permite anticipar las tasas de variación del producto interno bruto (PIB) trimestral.","dimensions":[{"label":"Vacunos","data":[{"x":"1980-01-01","y":1214174},{"x":"1980-02-01","y":1131932},{"x":"1980-03-01","y":1172202},{"x":"1980-04-01","y":1165997},{"x":"1980-05-01","y":1168835},{"x":"1980-06-01","y":1070184},{"x":"1980-07-01","y":1175414},{"x":"1980-08-01","y":1079374},{"x":"1980-09-01","y":1149710},{"x":"1980-10-01","y":1152313},{"x":"1980-11-01","y":1091288},{"x":"1980-12-01","y":1259073},{"x":"1981-01-01","y":1145988},{"x":"1981-02-01","y":1100071},{"x":"1981-03-01","y":1306508},{"x":"1981-04-01","y":1301459},{"x":"1981-05-01","y":1273451},{"x":"1981-06-01","y":1324364},{"x":"1981-07-01","y":1338243},{"x":"1981-08-01","y":1185581},{"x":"1981-09-01","y":1191823},{"x":"1981-10-01","y":1220387},{"x":"1981-11-01","y":1121893},{"x":"1981-12-01","y":1140727},{"x":"1982-01-01","y":1065677},{"x":"1982-02-01","y":1067102},{"x":"1982-03-01","y":1321472},{"x":"1982-04-01","y":1196339},{"x":"1982-05-01","y":1177383},{"x":"1982-06-01","y":1052155},{"x":"1982-07-01","y":1009072},{"x":"1982-08-01","y":1043927},{"x":"1982-09-01","y":843912},{"x":"1982-10-01","y":771754},{"x":"1982-11-01","y":887747},{"x":"1982-12-01","y":925511},{"x":"1983-01-01","y":908162},{"x":"1983-02-01","y":807973},{"x":"1983-03-01","y":1024813},{"x":"1983-04-01","y":951338},{"x":"1983-05-01","y":1052327},{"x":"1983-06-01","y":998737},{"x":"1983-07-01","y":963165},{"x":"1983-08-01","y":966395},{"x":"1983-09-01","y":877585},{"x":"1983-10-01","y":894381},{"x":"1983-11-01","y":966173},{"x":"1983-12-01","y":1014566},{"x":"1984-01-01","y":1019944},{"x":"1984-02-01","y":919164},{"x":"1984-03-01","y":980789},{"x":"1984-04-01","y":1045571},{"x":"1984-05-01","y":1180265},{"x":"1984-06-01","y":1063832},{"x":"1984-07-01","y":1078333},{"x":"1984-08-01","y":1060832},{"x":"1984-09-01","y":819612},{"x":"1984-10-01","y":1005605},{"x":"1984-11-01","y":1055710},{"x":"1984-12-01","y":991783},{"x":"1985-01-01","y":1175761},{"x":"1985-02-01","y":1072151},{"x":"1985-03-01","y":1215787},{"x":"1985-04-01","y":1316343},{"x":"1985-05-01","y":1385881},{"x":"1985-06-01","y":1096822},{"x":"1985-07-01","y":1216071},{"x":"1985-08-01","y":1154185},{"x":"1985-09-01","y":1081498},{"x":"1985-10-01","y":1095099},{"x":"1985-11-01","y":1057639},{"x":"1985-12-01","y":1183674},{"x":"1986-01-01","y":1252099},{"x":"1986-02-01","y":1149334},{"x":"1986-03-01","y":1251320},{"x":"1986-04-01","y":1377415},{"x":"1986-05-01","y":1320158},{"x":"1986-06-01","y":1207224},{"x":"1986-07-01","y":1269091},{"x":"1986-08-01","y":1150518},{"x":"1986-09-01","y":1197763},{"x":"1986-10-01","y":1240547},{"x":"1986-11-01","y":1135321},{"x":"1986-12-01","y":1298125},{"x":"1987-01-01","y":1159943},{"x":"1987-02-01","y":1070024},{"x":"1987-03-01","y":1207799},{"x":"1987-04-01","y":1152249},{"x":"1987-05-01","y":1094509},{"x":"1987-06-01","y":1152119},{"x":"1987-07-01","y":1067400},{"x":"1987-08-01","y":905656},{"x":"1987-09-01","y":987934},{"x":"1987-10-01","y":978300},{"x":"1987-11-01","y":1004858},{"x":"1987-12-01","y":1096967},{"x":"1988-01-01","y":969107},{"x":"1988-02-01","y":1003833},{"x":"1988-03-01","y":1091208},{"x":"1988-04-01","y":1041237},{"x":"1988-05-01","y":1111534},{"x":"1988-06-01","y":1065111},{"x":"1988-07-01","y":1023363},{"x":"1988-08-01","y":1032284},{"x":"1988-09-01","y":945636},{"x":"1988-10-01","y":888015},{"x":"1988-11-01","y":986677},{"x":"1988-12-01","y":1041996},{"x":"1989-01-01","y":1032627},{"x":"1989-02-01","y":961821},{"x":"1989-03-01","y":1106461},{"x":"1989-04-01","y":1072846},{"x":"1989-05-01","y":1146174},{"x":"1989-06-01","y":950922},{"x":"1989-07-01","y":882602},{"x":"1989-08-01","y":1030818},{"x":"1989-09-01","y":983663},{"x":"1989-10-01","y":1068935},{"x":"1989-11-01","y":1048034},{"x":"1989-12-01","y":925096},{"x":"1990-01-01","y":1088612},{"x":"1990-02-01","y":893810},{"x":"1990-03-01","y":1049045},{"x":"1990-04-01","y":1097533},{"x":"1990-05-01","y":1211668},{"x":"1990-06-01","y":1161577},{"x":"1990-07-01","y":1214380},{"x":"1990-08-01","y":1200601},{"x":"1990-09-01","y":1073793},{"x":"1990-10-01","y":1173370},{"x":"1990-11-01","y":1142646},{"x":"1990-12-01","y":1116543},{"x":"1991-01-01","y":1185848},{"x":"1991-02-01","y":1078564},{"x":"1991-03-01","y":1118599},{"x":"1991-04-01","y":1318063},{"x":"1991-05-01","y":1280815},{"x":"1991-06-01","y":1011945},{"x":"1991-07-01","y":1177470},{"x":"1991-08-01","y":1097158},{"x":"1991-09-01","y":987244},{"x":"1991-10-01","y":1102734},{"x":"1991-11-01","y":1036004},{"x":"1991-12-01","y":1121870},{"x":"1992-01-01","y":1143223},{"x":"1992-02-01","y":1032182},{"x":"1992-03-01","y":1142267},{"x":"1992-04-01","y":1108850},{"x":"1992-05-01","y":1013438},{"x":"1992-06-01","y":1065055},{"x":"1992-07-01","y":1130499},{"x":"1992-08-01","y":1023546},{"x":"1992-09-01","y":1016488},{"x":"1992-10-01","y":1057282},{"x":"1992-11-01","y":998194},{"x":"1992-12-01","y":1092883},{"x":"1993-01-01","y":1019803},{"x":"1993-02-01","y":1042110},{"x":"1993-03-01","y":1231476},{"x":"1993-04-01","y":1139142},{"x":"1993-05-01","y":1137513},{"x":"1993-06-01","y":1149935},{"x":"1993-07-01","y":1121799},{"x":"1993-08-01","y":1087711},{"x":"1993-09-01","y":1066271},{"x":"1993-10-01","y":1032993},{"x":"1993-11-01","y":1097963},{"x":"1993-12-01","y":1089883},{"x":"1994-01-01","y":1032357},{"x":"1994-02-01","y":996919},{"x":"1994-03-01","y":1162790},{"x":"1994-04-01","y":1060222},{"x":"1994-05-01","y":1137107},{"x":"1994-06-01","y":1111680},{"x":"1994-07-01","y":1111911},{"x":"1994-08-01","y":1111422},{"x":"1994-09-01","y":1082230},{"x":"1994-10-01","y":1091886},{"x":"1994-11-01","y":1181884},{"x":"1994-12-01","y":1119950},{"x":"1995-01-01","y":1097434},{"x":"1995-02-01","y":987285},{"x":"1995-03-01","y":1187209},{"x":"1995-04-01","y":1012913},{"x":"1995-05-01","y":1154424},{"x":"1995-06-01","y":1097922},{"x":"1995-07-01","y":1081237},{"x":"1995-08-01","y":1145916},{"x":"1995-09-01","y":1030984},{"x":"1995-10-01","y":1023800},{"x":"1995-11-01","y":1063022},{"x":"1995-12-01","y":975261},{"x":"1996-01-01","y":1048122},{"x":"1996-02-01","y":1018604},{"x":"1996-03-01","y":1080415},{"x":"1996-04-01","y":1071631},{"x":"1996-05-01","y":1101575},{"x":"1996-06-01","y":1013796},{"x":"1996-07-01","y":1147922},{"x":"1996-08-01","y":1087215},{"x":"1996-09-01","y":1066607},{"x":"1996-10-01","y":1157875},{"x":"1996-11-01","y":1062404},{"x":"1996-12-01","y":1060549},{"x":"1997-01-01","y":1046797},{"x":"1997-02-01","y":996988},{"x":"1997-03-01","y":1076010},{"x":"1997-04-01","y":1218636},{"x":"1997-05-01","y":1143246},{"x":"1997-06-01","y":1039182},{"x":"1997-07-01","y":1090037},{"x":"1997-08-01","y":1004227},{"x":"1997-09-01","y":1064479},{"x":"1997-10-01","y":1070150},{"x":"1997-11-01","y":955432},{"x":"1997-12-01","y":1089533},{"x":"1998-01-01","y":981503},{"x":"1998-02-01","y":889530},{"x":"1998-03-01","y":992968},{"x":"1998-04-01","y":936164},{"x":"1998-05-01","y":912879},{"x":"1998-06-01","y":909223},{"x":"1998-07-01","y":895015},{"x":"1998-08-01","y":871195},{"x":"1998-09-01","y":908890},{"x":"1998-10-01","y":953602},{"x":"1998-11-01","y":965913},{"x":"1998-12-01","y":1050844},{"x":"1999-01-01","y":948672},{"x":"1999-02-01","y":927260},{"x":"1999-03-01","y":1074506},{"x":"1999-04-01","y":963026},{"x":"1999-05-01","y":1006152},{"x":"1999-06-01","y":977610},{"x":"1999-07-01","y":981162},{"x":"1999-08-01","y":1021676},{"x":"1999-09-01","y":1025461},{"x":"1999-10-01","y":1021556},{"x":"1999-11-01","y":1098031},{"x":"1999-12-01","y":1099917},{"x":"2000-01-01","y":1041838},{"x":"2000-02-01","y":1005183},{"x":"2000-03-01","y":1137095},{"x":"2000-04-01","y":934731},{"x":"2000-05-01","y":1079383},{"x":"2000-06-01","y":1042738},{"x":"2000-07-01","y":1020005},{"x":"2000-08-01","y":1040549.5},{"x":"2000-09-01","y":1003889},{"x":"2000-10-01","y":998872.5},{"x":"2000-11-01","y":1053555.5},{"x":"2000-12-01","y":1042395},{"x":"2001-01-01","y":1047059.5},{"x":"2001-02-01","y":980606},{"x":"2001-03-01","y":1004051},{"x":"2001-04-01","y":937680.5},{"x":"2001-05-01","y":981754},{"x":"2001-06-01","y":938215},{"x":"2001-07-01","y":963735},{"x":"2001-08-01","y":976874},{"x":"2001-09-01","y":866959},{"x":"2001-10-01","y":995446},{"x":"2001-11-01","y":974489},{"x":"2001-12-01","y":919863},{"x":"2002-01-01","y":912176.5},{"x":"2002-02-01","y":905497.5},{"x":"2002-03-01","y":934541.5},{"x":"2002-04-01","y":1000300.5},{"x":"2002-05-01","y":1009796},{"x":"2002-06-01","y":1042875.5},{"x":"2002-07-01","y":1063835},{"x":"2002-08-01","y":916480.5},{"x":"2002-09-01","y":891494.5},{"x":"2002-10-01","y":954068},{"x":"2002-11-01","y":912140.5},{"x":"2002-12-01","y":956632},{"x":"2003-01-01","y":948290.83},{"x":"2003-02-01","y":865925.33},{"x":"2003-03-01","y":940911.83},{"x":"2003-04-01","y":994561.33},{"x":"2003-05-01","y":1011823.83},{"x":"2003-06-01","y":1022114.08},{"x":"2003-07-01","y":1111491.25},{"x":"2003-08-01","y":1042236},{"x":"2003-09-01","y":1113897.5},{"x":"2003-10-01","y":1174286},{"x":"2003-11-01","y":1088776},{"x":"2003-12-01","y":1217320},{"x":"2004-01-01","y":1113413.75},{"x":"2004-02-01","y":1084766.75},{"x":"2004-03-01","y":1239671},{"x":"2004-04-01","y":1110502},{"x":"2004-05-01","y":1192916},{"x":"2004-06-01","y":1256293},{"x":"2004-07-01","y":1230684},{"x":"2004-08-01","y":1231635},{"x":"2004-09-01","y":1215847},{"x":"2004-10-01","y":1181224},{"x":"2004-11-01","y":1226590},{"x":"2004-12-01","y":1248437},{"x":"2005-01-01","y":1128533},{"x":"2005-02-01","y":1092710},{"x":"2005-03-01","y":1136206},{"x":"2005-04-01","y":1211311},{"x":"2005-05-01","y":1270277},{"x":"2005-06-01","y":1218348},{"x":"2005-07-01","y":1201097},{"x":"2005-08-01","y":1279725},{"x":"2005-09-01","y":1246835},{"x":"2005-10-01","y":1234561},{"x":"2005-11-01","y":1186146},{"x":"2005-12-01","y":1144571},{"x":"2006-01-01","y":1138254},{"x":"2006-02-01","y":1007948},{"x":"2006-03-01","y":1114299},{"x":"2006-04-01","y":878694},{"x":"2006-05-01","y":1009348},{"x":"2006-06-01","y":1041743},{"x":"2006-07-01","y":1081878},{"x":"2006-08-01","y":1277126},{"x":"2006-09-01","y":1217509},{"x":"2006-10-01","y":1253146},{"x":"2006-11-01","y":1270595},{"x":"2006-12-01","y":1124620},{"x":"2007-01-01","y":1222573},{"x":"2007-02-01","y":1085812},{"x":"2007-03-01","y":1176370},{"x":"2007-04-01","y":1103249},{"x":"2007-05-01","y":1209901},{"x":"2007-06-01","y":1202138},{"x":"2007-07-01","y":1300901},{"x":"2007-08-01","y":1381501},{"x":"2007-09-01","y":1171053},{"x":"2007-10-01","y":1387410},{"x":"2007-11-01","y":1423321},{"x":"2007-12-01","y":1291430},{"x":"2008-01-01","y":1336470},{"x":"2008-02-01","y":1241836},{"x":"2008-03-01","y":722024},{"x":"2008-04-01","y":1379156},{"x":"2008-05-01","y":1103694},{"x":"2008-06-01","y":1023830},{"x":"2008-07-01","y":1370185},{"x":"2008-08-01","y":1300403},{"x":"2008-09-01","y":1364431},{"x":"2008-10-01","y":1332022},{"x":"2008-11-01","y":1181323},{"x":"2008-12-01","y":1304910},{"x":"2009-01-01","y":1311459},{"x":"2009-02-01","y":1213668},{"x":"2009-03-01","y":1259783},{"x":"2009-04-01","y":1342224.25},{"x":"2009-05-01","y":1241788},{"x":"2009-06-01","y":1427990},{"x":"2009-07-01","y":1458327.25},{"x":"2009-08-01","y":1390996},{"x":"2009-09-01","y":1333419},{"x":"2009-10-01","y":1439888},{"x":"2009-11-01","y":1324910},{"x":"2009-12-01","y":1308602},{"x":"2010-01-01","y":1133636},{"x":"2010-02-01","y":967760},{"x":"2010-03-01","y":1105605},{"x":"2010-04-01","y":974771},{"x":"2010-05-01","y":933997},{"x":"2010-06-01","y":951394},{"x":"2010-07-01","y":1009126},{"x":"2010-08-01","y":1049636},{"x":"2010-09-01","y":994473},{"x":"2010-10-01","y":895803.5},{"x":"2010-11-01","y":925595.5},{"x":"2010-12-01","y":940909},{"x":"2011-01-01","y":889059},{"x":"2011-02-01","y":851054.63},{"x":"2011-03-01","y":943434},{"x":"2011-04-01","y":821028.35},{"x":"2011-05-01","y":896681},{"x":"2011-06-01","y":880244},{"x":"2011-07-01","y":883661.33},{"x":"2011-08-01","y":954705.34},{"x":"2011-09-01","y":947363.76},{"x":"2011-10-01","y":919000.97},{"x":"2011-11-01","y":912402.78},{"x":"2011-12-01","y":963261.09},{"x":"2012-01-01","y":955814.17},{"x":"2012-02-01","y":894783.8},{"x":"2012-03-01","y":959587.5},{"x":"2012-04-01","y":854387.95},{"x":"2012-05-01","y":973059.63},{"x":"2012-06-01","y":879179.09},{"x":"2012-07-01","y":986917.01},{"x":"2012-08-01","y":959128.91},{"x":"2012-09-01","y":943420.55},{"x":"2012-10-01","y":1038945.75},{"x":"2012-11-01","y":995957.75},{"x":"2012-12-01","y":987609.29},{"x":"2013-01-01","y":1060153.25},{"x":"2013-02-01","y":969251.09},{"x":"2013-03-01","y":970461.61},{"x":"2013-04-01","y":1045237.89},{"x":"2013-05-01","y":1058122.36},{"x":"2013-06-01","y":989779.03},{"x":"2013-07-01","y":1133757.14},{"x":"2013-08-01","y":1049659.5},{"x":"2013-09-01","y":1071109.5},{"x":"2013-10-01","y":1161800.45},{"x":"2013-11-01","y":1030823.16},{"x":"2013-12-01","y":1085358},{"x":"2014-01-01","y":1052690.68},{"x":"2014-02-01","y":935530.68},{"x":"2014-03-01","y":996408.51},{"x":"2014-04-01","y":991565.47},{"x":"2014-05-01","y":1000823.28},{"x":"2014-06-01","y":1019093.47},{"x":"2014-07-01","y":1062187.07},{"x":"2014-08-01","y":958315.38},{"x":"2014-09-01","y":1028454.93},{"x":"2014-10-01","y":1032708.36},{"x":"2014-11-01","y":997488},{"x":"2014-12-01","y":1025713.18},{"x":"2015-01-01","y":1022228.3},{"x":"2015-02-01","y":945810.3},{"x":"2015-03-01","y":1069896.05},{"x":"2015-04-01","y":1010407.67},{"x":"2015-05-01","y":1006319.49},{"x":"2015-06-01","y":1071131.99},{"x":"2015-07-01","y":1028152.79},{"x":"2015-08-01","y":1002452.29},{"x":"2015-09-01","y":1066823.8},{"x":"2015-10-01","y":1009066.13},{"x":"2015-11-01","y":960241.65},{"x":"2015-12-01","y":964069.73},{"x":"2016-01-01","y":941113},{"x":"2016-02-01","y":913581},{"x":"2016-03-01","y":1010335},{"x":"2016-04-01","y":902498},{"x":"2016-05-01","y":985943},{"x":"2016-06-01","y":946228},{"x":"2016-07-01","y":928975},{"x":"2016-08-01","y":1038556},{"x":"2016-09-01","y":978182},{"x":"2016-10-01","y":977058},{"x":"2016-11-01","y":1029272},{"x":"2016-12-01","y":1068609},{"x":"2017-01-01","y":1035008.2},{"x":"2017-02-01","y":893067.75},{"x":"2017-03-01","y":1120895.5},{"x":"2017-04-01","y":915087.5},{"x":"2017-05-01","y":1060236},{"x":"2017-06-01","y":1043616.5},{"x":"2017-07-01","y":1020241.25},{"x":"2017-08-01","y":1098028},{"x":"2017-09-01","y":1046021.5},{"x":"2017-10-01","y":1130660.75},{"x":"2017-11-01","y":1124740.25},{"x":"2017-12-01","y":1106232},{"x":"2018-01-01","y":1113749.5},{"x":"2018-02-01","y":1015497.5},{"x":"2018-03-01","y":1144104.5},{"x":"2018-04-01","y":1097057.75},{"x":"2018-05-01","y":1141759},{"x":"2018-06-01","y":1108133.25},{"x":"2018-07-01","y":1128669.75},{"x":"2018-08-01","y":1187470.5},{"x":"2018-09-01","y":999702.75},{"x":"2018-10-01","y":1210403.75},{"x":"2018-11-01","y":1129335},{"x":"2018-12-01","y":1124253.25},{"x":"2019-01-01","y":1131196.25},{"x":"2019-02-01","y":983607},{"x":"2019-03-01","y":1019758.25},{"x":"2019-04-01","y":1072583.5},{"x":"2019-05-01","y":1174824.25},{"x":"2019-06-01","y":1052396.25},{"x":"2019-07-01","y":1267451.75},{"x":"2019-08-01","y":1198150.5},{"x":"2019-09-01","y":1191441.5},{"x":"2019-10-01","y":1308577.25},{"x":"2019-11-01","y":1205940.25},{"x":"2019-12-01","y":1266961.25},{"x":"2020-01-01","y":1143845.5},{"x":"2020-02-01","y":1013204.5},{"x":"2020-03-01","y":1095439.25},{"x":"2020-04-01","y":1170396.75},{"x":"2020-05-01","y":1145786.75},{"x":"2020-06-01","y":1201604.75},{"x":"2020-07-01","y":1211129.75},{"x":"2020-08-01","y":1156906.75},{"x":"2020-09-01","y":1210719},{"x":"2020-10-01","y":1234249.5},{"x":"2020-11-01","y":1224106},{"x":"2020-12-01","y":1200821},{"x":"2021-01-01","y":998607.25},{"x":"2021-02-01","y":1004790.5},{"x":"2021-03-01","y":1179206},{"x":"2021-04-01","y":1096978},{"x":"2021-05-01","y":982642.5},{"x":"2021-06-01","y":1089096.75},{"x":"2021-07-01","y":1074274.75},{"x":"2021-08-01","y":1139471.5},{"x":"2021-09-01","y":1099762.75},{"x":"2021-10-01","y":1076692.75},{"x":"2021-11-01","y":1103332.5},{"x":"2021-12-01","y":1142377},{"x":"2022-01-01","y":974681.75},{"x":"2022-02-01","y":1022410.5},{"x":"2022-03-01","y":1146743.75},{"x":"2022-04-01","y":1052178.25},{"x":"2022-05-01","y":1160459.75},{"x":"2022-06-01","y":1139703.75},{"x":"2022-07-01","y":1106239.75},{"x":"2022-08-01","y":1228282.5},{"x":"2022-09-01","y":1178209.5},{"x":"2022-10-01","y":1100755.75},{"x":"2022-11-01","y":1171284},{"x":"2022-12-01","y":1217784},{"x":"2023-01-01","y":1193795},{"x":"2023-02-01","y":1048049}]},{"label":"Ovinos","data":[{"x":"1980-01-01","y":0},{"x":"1980-02-01","y":0},{"x":"1980-03-01","y":0},{"x":"1980-04-01","y":0},{"x":"1980-05-01","y":0},{"x":"1980-06-01","y":0},{"x":"1980-07-01","y":0},{"x":"1980-08-01","y":0},{"x":"1980-09-01","y":0},{"x":"1980-10-01","y":0},{"x":"1980-11-01","y":0},{"x":"1980-12-01","y":0},{"x":"1981-01-01","y":0},{"x":"1981-02-01","y":0},{"x":"1981-03-01","y":0},{"x":"1981-04-01","y":0},{"x":"1981-05-01","y":0},{"x":"1981-06-01","y":0},{"x":"1981-07-01","y":0},{"x":"1981-08-01","y":0},{"x":"1981-09-01","y":0},{"x":"1981-10-01","y":0},{"x":"1981-11-01","y":0},{"x":"1981-12-01","y":0},{"x":"1982-01-01","y":0},{"x":"1982-02-01","y":0},{"x":"1982-03-01","y":0},{"x":"1982-04-01","y":0},{"x":"1982-05-01","y":0},{"x":"1982-06-01","y":0},{"x":"1982-07-01","y":0},{"x":"1982-08-01","y":0},{"x":"1982-09-01","y":0},{"x":"1982-10-01","y":0},{"x":"1982-11-01","y":0},{"x":"1982-12-01","y":0},{"x":"1983-01-01","y":0},{"x":"1983-02-01","y":0},{"x":"1983-03-01","y":0},{"x":"1983-04-01","y":0},{"x":"1983-05-01","y":0},{"x":"1983-06-01","y":0},{"x":"1983-07-01","y":0},{"x":"1983-08-01","y":0},{"x":"1983-09-01","y":0},{"x":"1983-10-01","y":0},{"x":"1983-11-01","y":0},{"x":"1983-12-01","y":0},{"x":"1984-01-01","y":0},{"x":"1984-02-01","y":0},{"x":"1984-03-01","y":0},{"x":"1984-04-01","y":0},{"x":"1984-05-01","y":0},{"x":"1984-06-01","y":0},{"x":"1984-07-01","y":0},{"x":"1984-08-01","y":0},{"x":"1984-09-01","y":0},{"x":"1984-10-01","y":0},{"x":"1984-11-01","y":0},{"x":"1984-12-01","y":0},{"x":"1985-01-01","y":0},{"x":"1985-02-01","y":0},{"x":"1985-03-01","y":0},{"x":"1985-04-01","y":0},{"x":"1985-05-01","y":0},{"x":"1985-06-01","y":0},{"x":"1985-07-01","y":0},{"x":"1985-08-01","y":0},{"x":"1985-09-01","y":0},{"x":"1985-10-01","y":0},{"x":"1985-11-01","y":0},{"x":"1985-12-01","y":0},{"x":"1986-01-01","y":0},{"x":"1986-02-01","y":0},{"x":"1986-03-01","y":0},{"x":"1986-04-01","y":0},{"x":"1986-05-01","y":0},{"x":"1986-06-01","y":0},{"x":"1986-07-01","y":0},{"x":"1986-08-01","y":0},{"x":"1986-09-01","y":0},{"x":"1986-10-01","y":0},{"x":"1986-11-01","y":0},{"x":"1986-12-01","y":0},{"x":"1987-01-01","y":0},{"x":"1987-02-01","y":0},{"x":"1987-03-01","y":0},{"x":"1987-04-01","y":0},{"x":"1987-05-01","y":0},{"x":"1987-06-01","y":0},{"x":"1987-07-01","y":0},{"x":"1987-08-01","y":0},{"x":"1987-09-01","y":0},{"x":"1987-10-01","y":0},{"x":"1987-11-01","y":0},{"x":"1987-12-01","y":0},{"x":"1988-01-01","y":0},{"x":"1988-02-01","y":0},{"x":"1988-03-01","y":0},{"x":"1988-04-01","y":0},{"x":"1988-05-01","y":0},{"x":"1988-06-01","y":0},{"x":"1988-07-01","y":0},{"x":"1988-08-01","y":0},{"x":"1988-09-01","y":0},{"x":"1988-10-01","y":0},{"x":"1988-11-01","y":0},{"x":"1988-12-01","y":0},{"x":"1989-01-01","y":0},{"x":"1989-02-01","y":0},{"x":"1989-03-01","y":0},{"x":"1989-04-01","y":0},{"x":"1989-05-01","y":0},{"x":"1989-06-01","y":0},{"x":"1989-07-01","y":0},{"x":"1989-08-01","y":0},{"x":"1989-09-01","y":0},{"x":"1989-10-01","y":0},{"x":"1989-11-01","y":0},{"x":"1989-12-01","y":0},{"x":"1990-01-01","y":0},{"x":"1990-02-01","y":0},{"x":"1990-03-01","y":0},{"x":"1990-04-01","y":0},{"x":"1990-05-01","y":0},{"x":"1990-06-01","y":0},{"x":"1990-07-01","y":0},{"x":"1990-08-01","y":0},{"x":"1990-09-01","y":0},{"x":"1990-10-01","y":0},{"x":"1990-11-01","y":0},{"x":"1990-12-01","y":0},{"x":"1991-01-01","y":0},{"x":"1991-02-01","y":0},{"x":"1991-03-01","y":0},{"x":"1991-04-01","y":0},{"x":"1991-05-01","y":0},{"x":"1991-06-01","y":0},{"x":"1991-07-01","y":0},{"x":"1991-08-01","y":0},{"x":"1991-09-01","y":0},{"x":"1991-10-01","y":0},{"x":"1991-11-01","y":0},{"x":"1991-12-01","y":0},{"x":"1992-01-01","y":0},{"x":"1992-02-01","y":0},{"x":"1992-03-01","y":0},{"x":"1992-04-01","y":0},{"x":"1992-05-01","y":0},{"x":"1992-06-01","y":0},{"x":"1992-07-01","y":0},{"x":"1992-08-01","y":0},{"x":"1992-09-01","y":0},{"x":"1992-10-01","y":0},{"x":"1992-11-01","y":0},{"x":"1992-12-01","y":0},{"x":"1993-01-01","y":0},{"x":"1993-02-01","y":0},{"x":"1993-03-01","y":0},{"x":"1993-04-01","y":0},{"x":"1993-05-01","y":0},{"x":"1993-06-01","y":0},{"x":"1993-07-01","y":0},{"x":"1993-08-01","y":0},{"x":"1993-09-01","y":0},{"x":"1993-10-01","y":0},{"x":"1993-11-01","y":0},{"x":"1993-12-01","y":0},{"x":"1994-01-01","y":0},{"x":"1994-02-01","y":0},{"x":"1994-03-01","y":0},{"x":"1994-04-01","y":0},{"x":"1994-05-01","y":0},{"x":"1994-06-01","y":0},{"x":"1994-07-01","y":0},{"x":"1994-08-01","y":0},{"x":"1994-09-01","y":0},{"x":"1994-10-01","y":0},{"x":"1994-11-01","y":0},{"x":"1994-12-01","y":0},{"x":"1995-01-01","y":0},{"x":"1995-02-01","y":0},{"x":"1995-03-01","y":0},{"x":"1995-04-01","y":0},{"x":"1995-05-01","y":0},{"x":"1995-06-01","y":0},{"x":"1995-07-01","y":0},{"x":"1995-08-01","y":0},{"x":"1995-09-01","y":0},{"x":"1995-10-01","y":0},{"x":"1995-11-01","y":0},{"x":"1995-12-01","y":0},{"x":"1996-01-01","y":0},{"x":"1996-02-01","y":0},{"x":"1996-03-01","y":0},{"x":"1996-04-01","y":0},{"x":"1996-05-01","y":0},{"x":"1996-06-01","y":0},{"x":"1996-07-01","y":0},{"x":"1996-08-01","y":0},{"x":"1996-09-01","y":0},{"x":"1996-10-01","y":0},{"x":"1996-11-01","y":0},{"x":"1996-12-01","y":0},{"x":"1997-01-01","y":0},{"x":"1997-02-01","y":0},{"x":"1997-03-01","y":0},{"x":"1997-04-01","y":0},{"x":"1997-05-01","y":0},{"x":"1997-06-01","y":0},{"x":"1997-07-01","y":0},{"x":"1997-08-01","y":0},{"x":"1997-09-01","y":0},{"x":"1997-10-01","y":0},{"x":"1997-11-01","y":0},{"x":"1997-12-01","y":0},{"x":"1998-01-01","y":0},{"x":"1998-02-01","y":0},{"x":"1998-03-01","y":0},{"x":"1998-04-01","y":0},{"x":"1998-05-01","y":0},{"x":"1998-06-01","y":0},{"x":"1998-07-01","y":0},{"x":"1998-08-01","y":0},{"x":"1998-09-01","y":0},{"x":"1998-10-01","y":0},{"x":"1998-11-01","y":0},{"x":"1998-12-01","y":0},{"x":"1999-01-01","y":0},{"x":"1999-02-01","y":0},{"x":"1999-03-01","y":0},{"x":"1999-04-01","y":0},{"x":"1999-05-01","y":0},{"x":"1999-06-01","y":0},{"x":"1999-07-01","y":0},{"x":"1999-08-01","y":0},{"x":"1999-09-01","y":0},{"x":"1999-10-01","y":0},{"x":"1999-11-01","y":0},{"x":"1999-12-01","y":0},{"x":"2000-01-01","y":0},{"x":"2000-02-01","y":0},{"x":"2000-03-01","y":0},{"x":"2000-04-01","y":0},{"x":"2000-05-01","y":0},{"x":"2000-06-01","y":0},{"x":"2000-07-01","y":0},{"x":"2000-08-01","y":0},{"x":"2000-09-01","y":0},{"x":"2000-10-01","y":0},{"x":"2000-11-01","y":0},{"x":"2000-12-01","y":0},{"x":"2001-01-01","y":0},{"x":"2001-02-01","y":0},{"x":"2001-03-01","y":0},{"x":"2001-04-01","y":0},{"x":"2001-05-01","y":0},{"x":"2001-06-01","y":0},{"x":"2001-07-01","y":0},{"x":"2001-08-01","y":0},{"x":"2001-09-01","y":0},{"x":"2001-10-01","y":0},{"x":"2001-11-01","y":0},{"x":"2001-12-01","y":0},{"x":"2002-01-01","y":0},{"x":"2002-02-01","y":0},{"x":"2002-03-01","y":0},{"x":"2002-04-01","y":0},{"x":"2002-05-01","y":0},{"x":"2002-06-01","y":0},{"x":"2002-07-01","y":0},{"x":"2002-08-01","y":0},{"x":"2002-09-01","y":0},{"x":"2002-10-01","y":0},{"x":"2002-11-01","y":0},{"x":"2002-12-01","y":0},{"x":"2003-01-01","y":0},{"x":"2003-02-01","y":0},{"x":"2003-03-01","y":0},{"x":"2003-04-01","y":0},{"x":"2003-05-01","y":0},{"x":"2003-06-01","y":0},{"x":"2003-07-01","y":0},{"x":"2003-08-01","y":0},{"x":"2003-09-01","y":0},{"x":"2003-10-01","y":0},{"x":"2003-11-01","y":0},{"x":"2003-12-01","y":0},{"x":"2004-01-01","y":0},{"x":"2004-02-01","y":0},{"x":"2004-03-01","y":0},{"x":"2004-04-01","y":0},{"x":"2004-05-01","y":0},{"x":"2004-06-01","y":0},{"x":"2004-07-01","y":0},{"x":"2004-08-01","y":0},{"x":"2004-09-01","y":0},{"x":"2004-10-01","y":0},{"x":"2004-11-01","y":0},{"x":"2004-12-01","y":0},{"x":"2005-01-01","y":0},{"x":"2005-02-01","y":0},{"x":"2005-03-01","y":0},{"x":"2005-04-01","y":0},{"x":"2005-05-01","y":0},{"x":"2005-06-01","y":0},{"x":"2005-07-01","y":0},{"x":"2005-08-01","y":0},{"x":"2005-09-01","y":0},{"x":"2005-10-01","y":0},{"x":"2005-11-01","y":0},{"x":"2005-12-01","y":0},{"x":"2006-01-01","y":0},{"x":"2006-02-01","y":0},{"x":"2006-03-01","y":0},{"x":"2006-04-01","y":0},{"x":"2006-05-01","y":0},{"x":"2006-06-01","y":0},{"x":"2006-07-01","y":0},{"x":"2006-08-01","y":0},{"x":"2006-09-01","y":0},{"x":"2006-10-01","y":0},{"x":"2006-11-01","y":0},{"x":"2006-12-01","y":0},{"x":"2007-01-01","y":0},{"x":"2007-02-01","y":0},{"x":"2007-03-01","y":0},{"x":"2007-04-01","y":0},{"x":"2007-05-01","y":0},{"x":"2007-06-01","y":0},{"x":"2007-07-01","y":0},{"x":"2007-08-01","y":0},{"x":"2007-09-01","y":0},{"x":"2007-10-01","y":0},{"x":"2007-11-01","y":0},{"x":"2007-12-01","y":0},{"x":"2008-01-01","y":0},{"x":"2008-02-01","y":0},{"x":"2008-03-01","y":0},{"x":"2008-04-01","y":0},{"x":"2008-05-01","y":0},{"x":"2008-06-01","y":0},{"x":"2008-07-01","y":0},{"x":"2008-08-01","y":0},{"x":"2008-09-01","y":0},{"x":"2008-10-01","y":0},{"x":"2008-11-01","y":0},{"x":"2008-12-01","y":0},{"x":"2009-01-01","y":0},{"x":"2009-02-01","y":0},{"x":"2009-03-01","y":0},{"x":"2009-04-01","y":0},{"x":"2009-05-01","y":0},{"x":"2009-06-01","y":0},{"x":"2009-07-01","y":0},{"x":"2009-08-01","y":0},{"x":"2009-09-01","y":0},{"x":"2009-10-01","y":0},{"x":"2009-11-01","y":0},{"x":"2009-12-01","y":0},{"x":"2010-01-01","y":0},{"x":"2010-02-01","y":0},{"x":"2010-03-01","y":0},{"x":"2010-04-01","y":0},{"x":"2010-05-01","y":0},{"x":"2010-06-01","y":0},{"x":"2010-07-01","y":0},{"x":"2010-08-01","y":0},{"x":"2010-09-01","y":0},{"x":"2010-10-01","y":0},{"x":"2010-11-01","y":0},{"x":"2010-12-01","y":0},{"x":"2011-01-01","y":0},{"x":"2011-02-01","y":0},{"x":"2011-03-01","y":0},{"x":"2011-04-01","y":0},{"x":"2011-05-01","y":0},{"x":"2011-06-01","y":0},{"x":"2011-07-01","y":0},{"x":"2011-08-01","y":0},{"x":"2011-09-01","y":0},{"x":"2011-10-01","y":0},{"x":"2011-11-01","y":0},{"x":"2011-12-01","y":0},{"x":"2012-01-01","y":0},{"x":"2012-02-01","y":0},{"x":"2012-03-01","y":0},{"x":"2012-04-01","y":0},{"x":"2012-05-01","y":0},{"x":"2012-06-01","y":0},{"x":"2012-07-01","y":0},{"x":"2012-08-01","y":0},{"x":"2012-09-01","y":0},{"x":"2012-10-01","y":0},{"x":"2012-11-01","y":0},{"x":"2012-12-01","y":0},{"x":"2013-01-01","y":0},{"x":"2013-02-01","y":0},{"x":"2013-03-01","y":0},{"x":"2013-04-01","y":0},{"x":"2013-05-01","y":0},{"x":"2013-06-01","y":0},{"x":"2013-07-01","y":0},{"x":"2013-08-01","y":0},{"x":"2013-09-01","y":0},{"x":"2013-10-01","y":0},{"x":"2013-11-01","y":0},{"x":"2013-12-01","y":0},{"x":"2014-01-01","y":0},{"x":"2014-02-01","y":0},{"x":"2014-03-01","y":0},{"x":"2014-04-01","y":0},{"x":"2014-05-01","y":0},{"x":"2014-06-01","y":0},{"x":"2014-07-01","y":0},{"x":"2014-08-01","y":0},{"x":"2014-09-01","y":0},{"x":"2014-10-01","y":0},{"x":"2014-11-01","y":0},{"x":"2014-12-01","y":0},{"x":"2015-01-01","y":0},{"x":"2015-02-01","y":0},{"x":"2015-03-01","y":0},{"x":"2015-04-01","y":0},{"x":"2015-05-01","y":0},{"x":"2015-06-01","y":0},{"x":"2015-07-01","y":0},{"x":"2015-08-01","y":0},{"x":"2015-09-01","y":0},{"x":"2015-10-01","y":0},{"x":"2015-11-01","y":0},{"x":"2015-12-01","y":0},{"x":"2016-01-01","y":0},{"x":"2016-02-01","y":0},{"x":"2016-03-01","y":0},{"x":"2016-04-01","y":0},{"x":"2016-05-01","y":0},{"x":"2016-06-01","y":0},{"x":"2016-07-01","y":0},{"x":"2016-08-01","y":0},{"x":"2016-09-01","y":0},{"x":"2016-10-01","y":0},{"x":"2016-11-01","y":0},{"x":"2016-12-01","y":0},{"x":"2017-01-01","y":0},{"x":"2017-02-01","y":0},{"x":"2017-03-01","y":0},{"x":"2017-04-01","y":0},{"x":"2017-05-01","y":0},{"x":"2017-06-01","y":0},{"x":"2017-07-01","y":0},{"x":"2017-08-01","y":0},{"x":"2017-09-01","y":0},{"x":"2017-10-01","y":0},{"x":"2017-11-01","y":0},{"x":"2017-12-01","y":0},{"x":"2018-01-01","y":191728},{"x":"2018-02-01","y":135418},{"x":"2018-03-01","y":103169},{"x":"2018-04-01","y":52591},{"x":"2018-05-01","y":39175},{"x":"2018-06-01","y":19744},{"x":"2018-07-01","y":17826},{"x":"2018-08-01","y":20849},{"x":"2018-09-01","y":13900},{"x":"2018-10-01","y":48006},{"x":"2018-11-01","y":63489},{"x":"2018-12-01","y":201257},{"x":"2019-01-01","y":176512},{"x":"2019-02-01","y":140475},{"x":"2019-03-01","y":109590},{"x":"2019-04-01","y":57474},{"x":"2019-05-01","y":37254},{"x":"2019-06-01","y":23807},{"x":"2019-07-01","y":18389},{"x":"2019-08-01","y":16968},{"x":"2019-09-01","y":19130},{"x":"2019-10-01","y":44980},{"x":"2019-11-01","y":69333},{"x":"2019-12-01","y":205087},{"x":"2020-01-01","y":191326},{"x":"2020-02-01","y":150992},{"x":"2020-03-01","y":93244},{"x":"2020-04-01","y":76148},{"x":"2020-05-01","y":43988},{"x":"2020-06-01","y":24834},{"x":"2020-07-01","y":16611},{"x":"2020-08-01","y":20802},{"x":"2020-09-01","y":23482},{"x":"2020-10-01","y":39144},{"x":"2020-11-01","y":60401},{"x":"2020-12-01","y":198624},{"x":"2021-01-01","y":165507},{"x":"2021-02-01","y":138454},{"x":"2021-03-01","y":107325},{"x":"2021-04-01","y":60714},{"x":"2021-05-01","y":36781},{"x":"2021-06-01","y":22250},{"x":"2021-07-01","y":22983},{"x":"2021-08-01","y":28732},{"x":"2021-09-01","y":23627},{"x":"2021-10-01","y":46773},{"x":"2021-11-01","y":84594},{"x":"2021-12-01","y":196535.9},{"x":"2022-01-01","y":149721},{"x":"2022-02-01","y":154389},{"x":"2022-03-01","y":129293},{"x":"2022-04-01","y":77627},{"x":"2022-05-01","y":54024},{"x":"2022-06-01","y":31172},{"x":"2022-07-01","y":22368},{"x":"2022-08-01","y":28079},{"x":"2022-09-01","y":27221},{"x":"2022-10-01","y":42167},{"x":"2022-11-01","y":0},{"x":"2022-12-01","y":0},{"x":"2023-01-01","y":175019},{"x":"2023-02-01","y":0}],"color":"rgba(46,120,210,0.3)"},{"label":"Porcinos","data":[{"x":"1980-01-01","y":199369},{"x":"1980-02-01","y":167072},{"x":"1980-03-01","y":189063},{"x":"1980-04-01","y":192268},{"x":"1980-05-01","y":181469},{"x":"1980-06-01","y":174511},{"x":"1980-07-01","y":212396},{"x":"1980-08-01","y":194332},{"x":"1980-09-01","y":223195},{"x":"1980-10-01","y":213736},{"x":"1980-11-01","y":201865},{"x":"1980-12-01","y":210379},{"x":"1981-01-01","y":172266},{"x":"1981-02-01","y":159823},{"x":"1981-03-01","y":195745},{"x":"1981-04-01","y":170062},{"x":"1981-05-01","y":173352},{"x":"1981-06-01","y":190784},{"x":"1981-07-01","y":183342},{"x":"1981-08-01","y":201064},{"x":"1981-09-01","y":217501},{"x":"1981-10-01","y":213224},{"x":"1981-11-01","y":195859},{"x":"1981-12-01","y":180627},{"x":"1982-01-01","y":164160},{"x":"1982-02-01","y":154115},{"x":"1982-03-01","y":178407},{"x":"1982-04-01","y":157449},{"x":"1982-05-01","y":159104},{"x":"1982-06-01","y":180280},{"x":"1982-07-01","y":173270},{"x":"1982-08-01","y":185235},{"x":"1982-09-01","y":184470},{"x":"1982-10-01","y":168304},{"x":"1982-11-01","y":178788},{"x":"1982-12-01","y":154325},{"x":"1983-01-01","y":121229},{"x":"1983-02-01","y":111077},{"x":"1983-03-01","y":122559},{"x":"1983-04-01","y":114836},{"x":"1983-05-01","y":123957},{"x":"1983-06-01","y":141593},{"x":"1983-07-01","y":124966},{"x":"1983-08-01","y":148161},{"x":"1983-09-01","y":143872},{"x":"1983-10-01","y":147452},{"x":"1983-11-01","y":159915},{"x":"1983-12-01","y":143675},{"x":"1984-01-01","y":134319},{"x":"1984-02-01","y":137958},{"x":"1984-03-01","y":133455},{"x":"1984-04-01","y":113247},{"x":"1984-05-01","y":131727},{"x":"1984-06-01","y":117544},{"x":"1984-07-01","y":153313},{"x":"1984-08-01","y":143642},{"x":"1984-09-01","y":133401},{"x":"1984-10-01","y":168008},{"x":"1984-11-01","y":130132},{"x":"1984-12-01","y":130427},{"x":"1985-01-01","y":130388},{"x":"1985-02-01","y":101299},{"x":"1985-03-01","y":118103},{"x":"1985-04-01","y":113065},{"x":"1985-05-01","y":109368},{"x":"1985-06-01","y":97245},{"x":"1985-07-01","y":136391},{"x":"1985-08-01","y":111345},{"x":"1985-09-01","y":126296},{"x":"1985-10-01","y":142173},{"x":"1985-11-01","y":120472},{"x":"1985-12-01","y":130584},{"x":"1986-01-01","y":115645},{"x":"1986-02-01","y":103918},{"x":"1986-03-01","y":109834},{"x":"1986-04-01","y":120289},{"x":"1986-05-01","y":121612},{"x":"1986-06-01","y":114750},{"x":"1986-07-01","y":140718},{"x":"1986-08-01","y":129039},{"x":"1986-09-01","y":147121},{"x":"1986-10-01","y":147647},{"x":"1986-11-01","y":138070},{"x":"1986-12-01","y":156001},{"x":"1987-01-01","y":136884},{"x":"1987-02-01","y":119902},{"x":"1987-03-01","y":150506},{"x":"1987-04-01","y":133165},{"x":"1987-05-01","y":138352},{"x":"1987-06-01","y":165336},{"x":"1987-07-01","y":151328},{"x":"1987-08-01","y":166217},{"x":"1987-09-01","y":178983},{"x":"1987-10-01","y":158426},{"x":"1987-11-01","y":160431},{"x":"1987-12-01","y":164408},{"x":"1988-01-01","y":139394},{"x":"1988-02-01","y":141961},{"x":"1988-03-01","y":149759},{"x":"1988-04-01","y":132433},{"x":"1988-05-01","y":145308},{"x":"1988-06-01","y":143519},{"x":"1988-07-01","y":140544},{"x":"1988-08-01","y":155615},{"x":"1988-09-01","y":138855},{"x":"1988-10-01","y":161782},{"x":"1988-11-01","y":164161},{"x":"1988-12-01","y":166066},{"x":"1989-01-01","y":146971},{"x":"1989-02-01","y":136494},{"x":"1989-03-01","y":138236},{"x":"1989-04-01","y":125963},{"x":"1989-05-01","y":104209},{"x":"1989-06-01","y":101801},{"x":"1989-07-01","y":98527},{"x":"1989-08-01","y":116125},{"x":"1989-09-01","y":119782},{"x":"1989-10-01","y":138521},{"x":"1989-11-01","y":136465},{"x":"1989-12-01","y":121646},{"x":"1990-01-01","y":92807},{"x":"1990-02-01","y":90019},{"x":"1990-03-01","y":79171},{"x":"1990-04-01","y":91739},{"x":"1990-05-01","y":99504},{"x":"1990-06-01","y":84244},{"x":"1990-07-01","y":97418},{"x":"1990-08-01","y":121386},{"x":"1990-09-01","y":110677},{"x":"1990-10-01","y":133663},{"x":"1990-11-01","y":116516},{"x":"1990-12-01","y":114093},{"x":"1991-01-01","y":116887},{"x":"1991-02-01","y":84045},{"x":"1991-03-01","y":92221},{"x":"1991-04-01","y":107375},{"x":"1991-05-01","y":104449},{"x":"1991-06-01","y":86148},{"x":"1991-07-01","y":114889},{"x":"1991-08-01","y":92352},{"x":"1991-09-01","y":106297},{"x":"1991-10-01","y":124107},{"x":"1991-11-01","y":83838},{"x":"1991-12-01","y":115614},{"x":"1992-01-01","y":115052},{"x":"1992-02-01","y":106900},{"x":"1992-03-01","y":120184},{"x":"1992-04-01","y":99752},{"x":"1992-05-01","y":97249},{"x":"1992-06-01","y":117572},{"x":"1992-07-01","y":116319},{"x":"1992-08-01","y":117146},{"x":"1992-09-01","y":127828},{"x":"1992-10-01","y":120148},{"x":"1992-11-01","y":77956},{"x":"1992-12-01","y":134707},{"x":"1993-01-01","y":120689},{"x":"1993-02-01","y":110932},{"x":"1993-03-01","y":134813},{"x":"1993-04-01","y":102024},{"x":"1993-05-01","y":123603},{"x":"1993-06-01","y":130128},{"x":"1993-07-01","y":122357},{"x":"1993-08-01","y":135287},{"x":"1993-09-01","y":132651},{"x":"1993-10-01","y":126020},{"x":"1993-11-01","y":143980},{"x":"1993-12-01","y":138387},{"x":"1994-01-01","y":121986},{"x":"1994-02-01","y":114832},{"x":"1994-03-01","y":138901},{"x":"1994-04-01","y":127612},{"x":"1994-05-01","y":138397},{"x":"1994-06-01","y":122221},{"x":"1994-07-01","y":112212},{"x":"1994-08-01","y":120941},{"x":"1994-09-01","y":127879},{"x":"1994-10-01","y":133518},{"x":"1994-11-01","y":149894},{"x":"1994-12-01","y":140883},{"x":"1995-01-01","y":124287},{"x":"1995-02-01","y":110623},{"x":"1995-03-01","y":121862},{"x":"1995-04-01","y":102288},{"x":"1995-05-01","y":119871},{"x":"1995-06-01","y":113964},{"x":"1995-07-01","y":106642},{"x":"1995-08-01","y":114210},{"x":"1995-09-01","y":109251},{"x":"1995-10-01","y":121657},{"x":"1995-11-01","y":115726},{"x":"1995-12-01","y":107670},{"x":"1996-01-01","y":106437},{"x":"1996-02-01","y":90640},{"x":"1996-03-01","y":94168},{"x":"1996-04-01","y":89251},{"x":"1996-05-01","y":78479},{"x":"1996-06-01","y":66444},{"x":"1996-07-01","y":75283},{"x":"1996-08-01","y":69245},{"x":"1996-09-01","y":73119},{"x":"1996-10-01","y":83917},{"x":"1996-11-01","y":77828},{"x":"1996-12-01","y":85284},{"x":"1997-01-01","y":112847},{"x":"1997-02-01","y":99131},{"x":"1997-03-01","y":107033},{"x":"1997-04-01","y":111302},{"x":"1997-05-01","y":104355},{"x":"1997-06-01","y":106256},{"x":"1997-07-01","y":116257},{"x":"1997-08-01","y":106437},{"x":"1997-09-01","y":131888},{"x":"1997-10-01","y":146353},{"x":"1997-11-01","y":147024},{"x":"1997-12-01","y":188040},{"x":"1998-01-01","y":117755},{"x":"1998-02-01","y":112142},{"x":"1998-03-01","y":130662},{"x":"1998-04-01","y":124034},{"x":"1998-05-01","y":125888},{"x":"1998-06-01","y":142946},{"x":"1998-07-01","y":137357},{"x":"1998-08-01","y":142281},{"x":"1998-09-01","y":154990},{"x":"1998-10-01","y":176102},{"x":"1998-11-01","y":199150},{"x":"1998-12-01","y":220042},{"x":"1999-01-01","y":163488},{"x":"1999-02-01","y":164539},{"x":"1999-03-01","y":194890},{"x":"1999-04-01","y":174853},{"x":"1999-05-01","y":195503},{"x":"1999-06-01","y":190309},{"x":"1999-07-01","y":186240},{"x":"1999-08-01","y":207476},{"x":"1999-09-01","y":206946},{"x":"1999-10-01","y":239120},{"x":"1999-11-01","y":273579},{"x":"1999-12-01","y":303768},{"x":"2000-01-01","y":189858},{"x":"2000-02-01","y":191164},{"x":"2000-03-01","y":206681},{"x":"2000-04-01","y":186245},{"x":"2000-05-01","y":214840},{"x":"2000-06-01","y":199775},{"x":"2000-07-01","y":198323},{"x":"2000-08-01","y":207659},{"x":"2000-09-01","y":197983},{"x":"2000-10-01","y":211381},{"x":"2000-11-01","y":233537},{"x":"2000-12-01","y":288072},{"x":"2001-01-01","y":197287},{"x":"2001-02-01","y":180974},{"x":"2001-03-01","y":195447},{"x":"2001-04-01","y":199578},{"x":"2001-05-01","y":203123},{"x":"2001-06-01","y":180652},{"x":"2001-07-01","y":199388},{"x":"2001-08-01","y":181935},{"x":"2001-09-01","y":182168},{"x":"2001-10-01","y":237868},{"x":"2001-11-01","y":244431},{"x":"2001-12-01","y":252600},{"x":"2002-01-01","y":158416},{"x":"2002-02-01","y":148074},{"x":"2002-03-01","y":143522},{"x":"2002-04-01","y":155054},{"x":"2002-05-01","y":148604},{"x":"2002-06-01","y":150835},{"x":"2002-07-01","y":178097},{"x":"2002-08-01","y":150409},{"x":"2002-09-01","y":163208},{"x":"2002-10-01","y":188725},{"x":"2002-11-01","y":190896},{"x":"2002-12-01","y":224025},{"x":"2003-01-01","y":138963},{"x":"2003-02-01","y":126956},{"x":"2003-03-01","y":132619},{"x":"2003-04-01","y":140512},{"x":"2003-05-01","y":136305},{"x":"2003-06-01","y":139850},{"x":"2003-07-01","y":149986},{"x":"2003-08-01","y":135286},{"x":"2003-09-01","y":164080},{"x":"2003-10-01","y":167816},{"x":"2003-11-01","y":171390},{"x":"2003-12-01","y":209164},{"x":"2004-01-01","y":133563},{"x":"2004-02-01","y":133888},{"x":"2004-03-01","y":166769},{"x":"2004-04-01","y":147170},{"x":"2004-05-01","y":166020},{"x":"2004-06-01","y":173274},{"x":"2004-07-01","y":168435},{"x":"2004-08-01","y":177240},{"x":"2004-09-01","y":191854},{"x":"2004-10-01","y":200458},{"x":"2004-11-01","y":230684},{"x":"2004-12-01","y":259154},{"x":"2005-01-01","y":165550},{"x":"2005-02-01","y":164643},{"x":"2005-03-01","y":185297},{"x":"2005-04-01","y":182334},{"x":"2005-05-01","y":194399},{"x":"2005-06-01","y":190762},{"x":"2005-07-01","y":190325},{"x":"2005-08-01","y":215420},{"x":"2005-09-01","y":209832},{"x":"2005-10-01","y":233719},{"x":"2005-11-01","y":260714},{"x":"2005-12-01","y":277129},{"x":"2006-01-01","y":207105},{"x":"2006-02-01","y":200637},{"x":"2006-03-01","y":226033},{"x":"2006-04-01","y":216248},{"x":"2006-05-01","y":258643},{"x":"2006-06-01","y":240591},{"x":"2006-07-01","y":257136},{"x":"2006-08-01","y":275000},{"x":"2006-09-01","y":267885},{"x":"2006-10-01","y":298359},{"x":"2006-11-01","y":298859},{"x":"2006-12-01","y":311480},{"x":"2007-01-01","y":261785},{"x":"2007-02-01","y":239293},{"x":"2007-03-01","y":263932},{"x":"2007-04-01","y":263342},{"x":"2007-05-01","y":275680},{"x":"2007-06-01","y":262640},{"x":"2007-07-01","y":268199},{"x":"2007-08-01","y":251921},{"x":"2007-09-01","y":237926},{"x":"2007-10-01","y":295248},{"x":"2007-11-01","y":287108},{"x":"2007-12-01","y":293081},{"x":"2008-01-01","y":226644},{"x":"2008-02-01","y":228125},{"x":"2008-03-01","y":166684},{"x":"2008-04-01","y":304544},{"x":"2008-05-01","y":254133},{"x":"2008-06-01","y":201336},{"x":"2008-07-01","y":301969},{"x":"2008-08-01","y":272550},{"x":"2008-09-01","y":296734},{"x":"2008-10-01","y":299071},{"x":"2008-11-01","y":279593},{"x":"2008-12-01","y":325458},{"x":"2009-01-01","y":252621},{"x":"2009-02-01","y":245190},{"x":"2009-03-01","y":269824},{"x":"2009-04-01","y":272071},{"x":"2009-05-01","y":251982},{"x":"2009-06-01","y":285377},{"x":"2009-07-01","y":283084},{"x":"2009-08-01","y":285751},{"x":"2009-09-01","y":280912},{"x":"2009-10-01","y":301385},{"x":"2009-11-01","y":287510},{"x":"2009-12-01","y":324052},{"x":"2010-01-01","y":249611},{"x":"2010-02-01","y":247473},{"x":"2010-03-01","y":300411},{"x":"2010-04-01","y":267682},{"x":"2010-05-01","y":260619},{"x":"2010-06-01","y":273321},{"x":"2010-07-01","y":268407},{"x":"2010-08-01","y":268464},{"x":"2010-09-01","y":255902},{"x":"2010-10-01","y":259664},{"x":"2010-11-01","y":277729},{"x":"2010-12-01","y":304850},{"x":"2011-01-01","y":240591},{"x":"2011-02-01","y":233186},{"x":"2011-03-01","y":272087},{"x":"2011-04-01","y":284850},{"x":"2011-05-01","y":300655},{"x":"2011-06-01","y":302116},{"x":"2011-07-01","y":300557},{"x":"2011-08-01","y":310593},{"x":"2011-09-01","y":285618},{"x":"2011-10-01","y":288392},{"x":"2011-11-01","y":288055},{"x":"2011-12-01","y":336060},{"x":"2012-01-01","y":275185},{"x":"2012-02-01","y":265643},{"x":"2012-03-01","y":332042},{"x":"2012-04-01","y":303752},{"x":"2012-05-01","y":339669},{"x":"2012-06-01","y":318305},{"x":"2012-07-01","y":335156},{"x":"2012-08-01","y":308693},{"x":"2012-09-01","y":304750},{"x":"2012-10-01","y":352152},{"x":"2012-11-01","y":342330},{"x":"2012-12-01","y":341081},{"x":"2013-01-01","y":365158},{"x":"2013-02-01","y":336332},{"x":"2013-03-01","y":374171},{"x":"2013-04-01","y":395605},{"x":"2013-05-01","y":411975},{"x":"2013-06-01","y":371801},{"x":"2013-07-01","y":421748},{"x":"2013-08-01","y":410133},{"x":"2013-09-01","y":411540},{"x":"2013-10-01","y":429360},{"x":"2013-11-01","y":414581},{"x":"2013-12-01","y":463095},{"x":"2014-01-01","y":398208},{"x":"2014-02-01","y":367192},{"x":"2014-03-01","y":430707},{"x":"2014-04-01","y":400829},{"x":"2014-05-01","y":446633},{"x":"2014-06-01","y":432264},{"x":"2014-07-01","y":430783},{"x":"2014-08-01","y":427505},{"x":"2014-09-01","y":443929},{"x":"2014-10-01","y":446474},{"x":"2014-11-01","y":421620},{"x":"2014-12-01","y":463939},{"x":"2015-01-01","y":417548},{"x":"2015-02-01","y":394202},{"x":"2015-03-01","y":452131},{"x":"2015-04-01","y":453275},{"x":"2015-05-01","y":450733},{"x":"2015-06-01","y":466867},{"x":"2015-07-01","y":455433},{"x":"2015-08-01","y":469502},{"x":"2015-09-01","y":479698},{"x":"2015-10-01","y":488840},{"x":"2015-11-01","y":490229},{"x":"2015-12-01","y":505257},{"x":"2016-01-01","y":455627},{"x":"2016-02-01","y":443309},{"x":"2016-03-01","y":518794},{"x":"2016-04-01","y":477071},{"x":"2016-05-01","y":523687},{"x":"2016-06-01","y":488628},{"x":"2016-07-01","y":503998},{"x":"2016-08-01","y":531490},{"x":"2016-09-01","y":486206},{"x":"2016-10-01","y":519855},{"x":"2016-11-01","y":493708},{"x":"2016-12-01","y":544188},{"x":"2017-01-01","y":478343},{"x":"2017-02-01","y":425739.75},{"x":"2017-03-01","y":542037.75},{"x":"2017-04-01","y":488422.75},{"x":"2017-05-01","y":566739.25},{"x":"2017-06-01","y":528149.5},{"x":"2017-07-01","y":536298.25},{"x":"2017-08-01","y":559567},{"x":"2017-09-01","y":529589.75},{"x":"2017-10-01","y":566862.75},{"x":"2017-11-01","y":538451},{"x":"2017-12-01","y":564878},{"x":"2018-01-01","y":528249.75},{"x":"2018-02-01","y":476967.5},{"x":"2018-03-01","y":553671.5},{"x":"2018-04-01","y":540171.75},{"x":"2018-05-01","y":566512},{"x":"2018-06-01","y":557306.75},{"x":"2018-07-01","y":583942},{"x":"2018-08-01","y":581938},{"x":"2018-09-01","y":515434.75},{"x":"2018-10-01","y":605628.75},{"x":"2018-11-01","y":549559.75},{"x":"2018-12-01","y":593705.5},{"x":"2019-01-01","y":544874.25},{"x":"2019-02-01","y":508582},{"x":"2019-03-01","y":540035},{"x":"2019-04-01","y":591622.5},{"x":"2019-05-01","y":594225.5},{"x":"2019-06-01","y":529308},{"x":"2019-07-01","y":612698.75},{"x":"2019-08-01","y":550787.25},{"x":"2019-09-01","y":540183.25},{"x":"2019-10-01","y":581622.75},{"x":"2019-11-01","y":536451.5},{"x":"2019-12-01","y":616852.5},{"x":"2020-01-01","y":559153},{"x":"2020-02-01","y":511173},{"x":"2020-03-01","y":521603},{"x":"2020-04-01","y":558981},{"x":"2020-05-01","y":569806},{"x":"2020-06-01","y":652479},{"x":"2020-07-01","y":619706},{"x":"2020-08-01","y":601284},{"x":"2020-09-01","y":589329},{"x":"2020-10-01","y":583660},{"x":"2020-11-01","y":580317},{"x":"2020-12-01","y":658603},{"x":"2021-01-01","y":555168},{"x":"2021-02-01","y":554228},{"x":"2021-03-01","y":678116},{"x":"2021-04-01","y":611120},{"x":"2021-05-01","y":617936},{"x":"2021-06-01","y":664719},{"x":"2021-07-01","y":642698},{"x":"2021-08-01","y":642229},{"x":"2021-09-01","y":608480},{"x":"2021-10-01","y":597511},{"x":"2021-11-01","y":634751},{"x":"2021-12-01","y":677315},{"x":"2022-01-01","y":534899},{"x":"2022-02-01","y":551528},{"x":"2022-03-01","y":669294},{"x":"2022-04-01","y":627197},{"x":"2022-05-01","y":679723},{"x":"2022-06-01","y":665740},{"x":"2022-07-01","y":652551},{"x":"2022-08-01","y":692582},{"x":"2022-09-01","y":636146},{"x":"2022-10-01","y":631920},{"x":"2022-11-01","y":649855},{"x":"2022-12-01","y":674578},{"x":"2023-01-01","y":634125},{"x":"2023-02-01","y":0}],"color":"rgba(46,120,210,0.6)"},{"label":"Aves","data":[{"x":"1980-01-01","y":0},{"x":"1980-02-01","y":0},{"x":"1980-03-01","y":0},{"x":"1980-04-01","y":0},{"x":"1980-05-01","y":0},{"x":"1980-06-01","y":0},{"x":"1980-07-01","y":0},{"x":"1980-08-01","y":0},{"x":"1980-09-01","y":0},{"x":"1980-10-01","y":0},{"x":"1980-11-01","y":0},{"x":"1980-12-01","y":0},{"x":"1981-01-01","y":0},{"x":"1981-02-01","y":0},{"x":"1981-03-01","y":0},{"x":"1981-04-01","y":0},{"x":"1981-05-01","y":0},{"x":"1981-06-01","y":0},{"x":"1981-07-01","y":0},{"x":"1981-08-01","y":0},{"x":"1981-09-01","y":0},{"x":"1981-10-01","y":0},{"x":"1981-11-01","y":0},{"x":"1981-12-01","y":0},{"x":"1982-01-01","y":0},{"x":"1982-02-01","y":0},{"x":"1982-03-01","y":0},{"x":"1982-04-01","y":0},{"x":"1982-05-01","y":0},{"x":"1982-06-01","y":0},{"x":"1982-07-01","y":0},{"x":"1982-08-01","y":0},{"x":"1982-09-01","y":0},{"x":"1982-10-01","y":0},{"x":"1982-11-01","y":0},{"x":"1982-12-01","y":0},{"x":"1983-01-01","y":0},{"x":"1983-02-01","y":0},{"x":"1983-03-01","y":0},{"x":"1983-04-01","y":0},{"x":"1983-05-01","y":0},{"x":"1983-06-01","y":0},{"x":"1983-07-01","y":0},{"x":"1983-08-01","y":0},{"x":"1983-09-01","y":0},{"x":"1983-10-01","y":0},{"x":"1983-11-01","y":0},{"x":"1983-12-01","y":0},{"x":"1984-01-01","y":0},{"x":"1984-02-01","y":0},{"x":"1984-03-01","y":0},{"x":"1984-04-01","y":0},{"x":"1984-05-01","y":0},{"x":"1984-06-01","y":0},{"x":"1984-07-01","y":0},{"x":"1984-08-01","y":0},{"x":"1984-09-01","y":0},{"x":"1984-10-01","y":0},{"x":"1984-11-01","y":0},{"x":"1984-12-01","y":0},{"x":"1985-01-01","y":0},{"x":"1985-02-01","y":0},{"x":"1985-03-01","y":0},{"x":"1985-04-01","y":0},{"x":"1985-05-01","y":0},{"x":"1985-06-01","y":0},{"x":"1985-07-01","y":0},{"x":"1985-08-01","y":0},{"x":"1985-09-01","y":0},{"x":"1985-10-01","y":0},{"x":"1985-11-01","y":0},{"x":"1985-12-01","y":0},{"x":"1986-01-01","y":0},{"x":"1986-02-01","y":0},{"x":"1986-03-01","y":0},{"x":"1986-04-01","y":0},{"x":"1986-05-01","y":0},{"x":"1986-06-01","y":0},{"x":"1986-07-01","y":0},{"x":"1986-08-01","y":0},{"x":"1986-09-01","y":0},{"x":"1986-10-01","y":0},{"x":"1986-11-01","y":0},{"x":"1986-12-01","y":0},{"x":"1987-01-01","y":0},{"x":"1987-02-01","y":0},{"x":"1987-03-01","y":0},{"x":"1987-04-01","y":0},{"x":"1987-05-01","y":0},{"x":"1987-06-01","y":0},{"x":"1987-07-01","y":0},{"x":"1987-08-01","y":0},{"x":"1987-09-01","y":0},{"x":"1987-10-01","y":0},{"x":"1987-11-01","y":0},{"x":"1987-12-01","y":0},{"x":"1988-01-01","y":0},{"x":"1988-02-01","y":0},{"x":"1988-03-01","y":0},{"x":"1988-04-01","y":0},{"x":"1988-05-01","y":0},{"x":"1988-06-01","y":0},{"x":"1988-07-01","y":0},{"x":"1988-08-01","y":0},{"x":"1988-09-01","y":0},{"x":"1988-10-01","y":0},{"x":"1988-11-01","y":0},{"x":"1988-12-01","y":0},{"x":"1989-01-01","y":0},{"x":"1989-02-01","y":0},{"x":"1989-03-01","y":0},{"x":"1989-04-01","y":0},{"x":"1989-05-01","y":0},{"x":"1989-06-01","y":0},{"x":"1989-07-01","y":0},{"x":"1989-08-01","y":0},{"x":"1989-09-01","y":0},{"x":"1989-10-01","y":0},{"x":"1989-11-01","y":0},{"x":"1989-12-01","y":0},{"x":"1990-01-01","y":0},{"x":"1990-02-01","y":0},{"x":"1990-03-01","y":0},{"x":"1990-04-01","y":0},{"x":"1990-05-01","y":0},{"x":"1990-06-01","y":0},{"x":"1990-07-01","y":0},{"x":"1990-08-01","y":0},{"x":"1990-09-01","y":0},{"x":"1990-10-01","y":0},{"x":"1990-11-01","y":0},{"x":"1990-12-01","y":0},{"x":"1991-01-01","y":0},{"x":"1991-02-01","y":0},{"x":"1991-03-01","y":0},{"x":"1991-04-01","y":0},{"x":"1991-05-01","y":0},{"x":"1991-06-01","y":0},{"x":"1991-07-01","y":0},{"x":"1991-08-01","y":0},{"x":"1991-09-01","y":0},{"x":"1991-10-01","y":0},{"x":"1991-11-01","y":0},{"x":"1991-12-01","y":0},{"x":"1992-01-01","y":0},{"x":"1992-02-01","y":0},{"x":"1992-03-01","y":0},{"x":"1992-04-01","y":0},{"x":"1992-05-01","y":0},{"x":"1992-06-01","y":0},{"x":"1992-07-01","y":0},{"x":"1992-08-01","y":0},{"x":"1992-09-01","y":0},{"x":"1992-10-01","y":0},{"x":"1992-11-01","y":0},{"x":"1992-12-01","y":0},{"x":"1993-01-01","y":0},{"x":"1993-02-01","y":0},{"x":"1993-03-01","y":0},{"x":"1993-04-01","y":0},{"x":"1993-05-01","y":0},{"x":"1993-06-01","y":0},{"x":"1993-07-01","y":0},{"x":"1993-08-01","y":0},{"x":"1993-09-01","y":0},{"x":"1993-10-01","y":0},{"x":"1993-11-01","y":0},{"x":"1993-12-01","y":0},{"x":"1994-01-01","y":0},{"x":"1994-02-01","y":0},{"x":"1994-03-01","y":0},{"x":"1994-04-01","y":0},{"x":"1994-05-01","y":0},{"x":"1994-06-01","y":0},{"x":"1994-07-01","y":0},{"x":"1994-08-01","y":0},{"x":"1994-09-01","y":0},{"x":"1994-10-01","y":0},{"x":"1994-11-01","y":0},{"x":"1994-12-01","y":0},{"x":"1995-01-01","y":0},{"x":"1995-02-01","y":0},{"x":"1995-03-01","y":0},{"x":"1995-04-01","y":0},{"x":"1995-05-01","y":0},{"x":"1995-06-01","y":0},{"x":"1995-07-01","y":0},{"x":"1995-08-01","y":0},{"x":"1995-09-01","y":0},{"x":"1995-10-01","y":0},{"x":"1995-11-01","y":0},{"x":"1995-12-01","y":0},{"x":"1996-01-01","y":0},{"x":"1996-02-01","y":0},{"x":"1996-03-01","y":0},{"x":"1996-04-01","y":0},{"x":"1996-05-01","y":0},{"x":"1996-06-01","y":0},{"x":"1996-07-01","y":0},{"x":"1996-08-01","y":0},{"x":"1996-09-01","y":0},{"x":"1996-10-01","y":0},{"x":"1996-11-01","y":0},{"x":"1996-12-01","y":0},{"x":"1997-01-01","y":0},{"x":"1997-02-01","y":0},{"x":"1997-03-01","y":0},{"x":"1997-04-01","y":0},{"x":"1997-05-01","y":0},{"x":"1997-06-01","y":0},{"x":"1997-07-01","y":0},{"x":"1997-08-01","y":0},{"x":"1997-09-01","y":0},{"x":"1997-10-01","y":0},{"x":"1997-11-01","y":0},{"x":"1997-12-01","y":0},{"x":"1998-01-01","y":0},{"x":"1998-02-01","y":0},{"x":"1998-03-01","y":0},{"x":"1998-04-01","y":0},{"x":"1998-05-01","y":0},{"x":"1998-06-01","y":0},{"x":"1998-07-01","y":0},{"x":"1998-08-01","y":0},{"x":"1998-09-01","y":0},{"x":"1998-10-01","y":0},{"x":"1998-11-01","y":0},{"x":"1998-12-01","y":0},{"x":"1999-01-01","y":0},{"x":"1999-02-01","y":0},{"x":"1999-03-01","y":0},{"x":"1999-04-01","y":0},{"x":"1999-05-01","y":0},{"x":"1999-06-01","y":0},{"x":"1999-07-01","y":0},{"x":"1999-08-01","y":0},{"x":"1999-09-01","y":0},{"x":"1999-10-01","y":0},{"x":"1999-11-01","y":0},{"x":"1999-12-01","y":0},{"x":"2000-01-01","y":0},{"x":"2000-02-01","y":0},{"x":"2000-03-01","y":0},{"x":"2000-04-01","y":0},{"x":"2000-05-01","y":0},{"x":"2000-06-01","y":0},{"x":"2000-07-01","y":0},{"x":"2000-08-01","y":0},{"x":"2000-09-01","y":0},{"x":"2000-10-01","y":0},{"x":"2000-11-01","y":0},{"x":"2000-12-01","y":0},{"x":"2001-01-01","y":0},{"x":"2001-02-01","y":0},{"x":"2001-03-01","y":0},{"x":"2001-04-01","y":0},{"x":"2001-05-01","y":0},{"x":"2001-06-01","y":0},{"x":"2001-07-01","y":0},{"x":"2001-08-01","y":0},{"x":"2001-09-01","y":0},{"x":"2001-10-01","y":0},{"x":"2001-11-01","y":0},{"x":"2001-12-01","y":0},{"x":"2002-01-01","y":0},{"x":"2002-02-01","y":0},{"x":"2002-03-01","y":0},{"x":"2002-04-01","y":0},{"x":"2002-05-01","y":0},{"x":"2002-06-01","y":0},{"x":"2002-07-01","y":0},{"x":"2002-08-01","y":0},{"x":"2002-09-01","y":0},{"x":"2002-10-01","y":0},{"x":"2002-11-01","y":0},{"x":"2002-12-01","y":0},{"x":"2003-01-01","y":0},{"x":"2003-02-01","y":0},{"x":"2003-03-01","y":0},{"x":"2003-04-01","y":0},{"x":"2003-05-01","y":0},{"x":"2003-06-01","y":0},{"x":"2003-07-01","y":0},{"x":"2003-08-01","y":0},{"x":"2003-09-01","y":0},{"x":"2003-10-01","y":0},{"x":"2003-11-01","y":0},{"x":"2003-12-01","y":0},{"x":"2004-01-01","y":0},{"x":"2004-02-01","y":0},{"x":"2004-03-01","y":0},{"x":"2004-04-01","y":0},{"x":"2004-05-01","y":0},{"x":"2004-06-01","y":0},{"x":"2004-07-01","y":0},{"x":"2004-08-01","y":0},{"x":"2004-09-01","y":0},{"x":"2004-10-01","y":0},{"x":"2004-11-01","y":0},{"x":"2004-12-01","y":0},{"x":"2005-01-01","y":0},{"x":"2005-02-01","y":0},{"x":"2005-03-01","y":0},{"x":"2005-04-01","y":0},{"x":"2005-05-01","y":0},{"x":"2005-06-01","y":0},{"x":"2005-07-01","y":0},{"x":"2005-08-01","y":0},{"x":"2005-09-01","y":0},{"x":"2005-10-01","y":0},{"x":"2005-11-01","y":0},{"x":"2005-12-01","y":0},{"x":"2006-01-01","y":17985.3},{"x":"2006-02-01","y":17584.6},{"x":"2006-03-01","y":19930.7},{"x":"2006-04-01","y":19503.4},{"x":"2006-05-01","y":23271.8},{"x":"2006-06-01","y":21383.7},{"x":"2006-07-01","y":22499.1},{"x":"2006-08-01","y":23865.5},{"x":"2006-09-01","y":23163.8},{"x":"2006-10-01","y":25313.8},{"x":"2006-11-01","y":24923.6},{"x":"2006-12-01","y":25621.5},{"x":"2007-01-01","y":22525.1},{"x":"2007-02-01","y":20468.3},{"x":"2007-03-01","y":22856.2},{"x":"2007-04-01","y":23085.2},{"x":"2007-05-01","y":24122.6},{"x":"2007-06-01","y":23015.8},{"x":"2007-07-01","y":23294.6},{"x":"2007-08-01","y":21976.8},{"x":"2007-09-01","y":20669.6},{"x":"2007-10-01","y":25277.7},{"x":"2007-11-01","y":23099.4},{"x":"2007-12-01","y":23727.2},{"x":"2008-01-01","y":19313},{"x":"2008-02-01","y":19289},{"x":"2008-03-01","y":14352},{"x":"2008-04-01","y":27597},{"x":"2008-05-01","y":22640},{"x":"2008-06-01","y":18104},{"x":"2008-07-01","y":27025},{"x":"2008-08-01","y":24101},{"x":"2008-09-01","y":26043},{"x":"2008-10-01","y":25346},{"x":"2008-11-01","y":23762},{"x":"2008-12-01","y":26783},{"x":"2009-01-01","y":21771},{"x":"2009-02-01","y":21061},{"x":"2009-03-01","y":23552},{"x":"2009-04-01","y":24268},{"x":"2009-05-01","y":22596},{"x":"2009-06-01","y":25557},{"x":"2009-07-01","y":24913},{"x":"2009-08-01","y":24747},{"x":"2009-09-01","y":24148},{"x":"2009-10-01","y":25583},{"x":"2009-11-01","y":24129},{"x":"2009-12-01","y":26528},{"x":"2010-01-01","y":21357},{"x":"2010-02-01","y":21086},{"x":"2010-03-01","y":25818},{"x":"2010-04-01","y":23407},{"x":"2010-05-01","y":23168},{"x":"2010-06-01","y":24333},{"x":"2010-07-01","y":23720},{"x":"2010-08-01","y":23449},{"x":"2010-09-01","y":22323},{"x":"2010-10-01","y":22588},{"x":"2010-11-01","y":23407},{"x":"2010-12-01","y":24446},{"x":"2011-01-01","y":21011},{"x":"2011-02-01","y":20224},{"x":"2011-03-01","y":23843},{"x":"2011-04-01","y":25765},{"x":"2011-05-01","y":27285},{"x":"2011-06-01","y":27273},{"x":"2011-07-01","y":26825},{"x":"2011-08-01","y":27323},{"x":"2011-09-01","y":25055},{"x":"2011-10-01","y":25074},{"x":"2011-11-01","y":24316},{"x":"2011-12-01","y":27301},{"x":"2012-01-01","y":22736},{"x":"2012-02-01","y":22378},{"x":"2012-03-01","y":28778},{"x":"2012-04-01","y":26818},{"x":"2012-05-01","y":29989},{"x":"2012-06-01","y":28103},{"x":"2012-07-01","y":29319},{"x":"2012-08-01","y":26754},{"x":"2012-09-01","y":26906},{"x":"2012-10-01","y":31092},{"x":"2012-11-01","y":29670},{"x":"2012-12-01","y":28456},{"x":"2013-01-01","y":30465},{"x":"2013-02-01","y":28333},{"x":"2013-03-01","y":32429},{"x":"2013-04-01","y":35569},{"x":"2013-05-01","y":37041},{"x":"2013-06-01","y":33429},{"x":"2013-07-01","y":37919},{"x":"2013-08-01","y":36211},{"x":"2013-09-01","y":35668},{"x":"2013-10-01","y":36865},{"x":"2013-11-01","y":34253},{"x":"2013-12-01","y":38261},{"x":"2014-01-01","y":33222},{"x":"2014-02-01","y":30635},{"x":"2014-03-01","y":37329},{"x":"2014-04-01","y":35714},{"x":"2014-05-01","y":40157},{"x":"2014-06-01","y":38165},{"x":"2014-07-01","y":37685},{"x":"2014-08-01","y":37398},{"x":"2014-09-01","y":38835},{"x":"2014-10-01","y":38696},{"x":"2014-11-01","y":35859},{"x":"2014-12-01","y":38331},{"x":"2015-01-01","y":35512},{"x":"2015-02-01","y":33208},{"x":"2015-03-01","y":39186},{"x":"2015-04-01","y":40020},{"x":"2015-05-01","y":40525},{"x":"2015-06-01","y":42354},{"x":"2015-07-01","y":40579},{"x":"2015-08-01","y":41452},{"x":"2015-09-01","y":42741},{"x":"2015-10-01","y":42764},{"x":"2015-11-01","y":42885},{"x":"2015-12-01","y":42972},{"x":"2016-01-01","y":39603},{"x":"2016-02-01","y":37442},{"x":"2016-03-01","y":44668},{"x":"2016-04-01","y":41467},{"x":"2016-05-01","y":47666},{"x":"2016-06-01","y":44475},{"x":"2016-07-01","y":45461},{"x":"2016-08-01","y":46197},{"x":"2016-09-01","y":42261},{"x":"2016-10-01","y":44760},{"x":"2016-11-01","y":42913},{"x":"2016-12-01","y":45516},{"x":"2017-01-01","y":40134.59},{"x":"2017-02-01","y":35946.46},{"x":"2017-03-01","y":46653.64},{"x":"2017-04-01","y":43077.21},{"x":"2017-05-01","y":50941.4},{"x":"2017-06-01","y":47887.12},{"x":"2017-07-01","y":48653.75},{"x":"2017-08-01","y":50196.55},{"x":"2017-09-01","y":47380.24},{"x":"2017-10-01","y":49862.59},{"x":"2017-11-01","y":46457.66},{"x":"2017-12-01","y":47173.28},{"x":"2018-01-01","y":45609.69},{"x":"2018-02-01","y":41637.46},{"x":"2018-03-01","y":48697.5},{"x":"2018-04-01","y":48471.32},{"x":"2018-05-01","y":51597.42},{"x":"2018-06-01","y":50530.31},{"x":"2018-07-01","y":52621.42},{"x":"2018-08-01","y":52299.05},{"x":"2018-09-01","y":45980.82},{"x":"2018-10-01","y":53193.28},{"x":"2018-11-01","y":47838.51},{"x":"2018-12-01","y":49891.43},{"x":"2019-01-01","y":48151.79},{"x":"2019-02-01","y":44518.3},{"x":"2019-03-01","y":48175.98},{"x":"2019-04-01","y":53751.25},{"x":"2019-05-01","y":54967.04},{"x":"2019-06-01","y":49162.44},{"x":"2019-07-01","y":56435.09},{"x":"2019-08-01","y":50540.47},{"x":"2019-09-01","y":49603.82},{"x":"2019-10-01","y":53183.91},{"x":"2019-11-01","y":48081.14},{"x":"2019-12-01","y":53754.5},{"x":"2020-01-01","y":50198},{"x":"2020-02-01","y":46039},{"x":"2020-03-01","y":48129},{"x":"2020-04-01","y":54073},{"x":"2020-05-01","y":55804},{"x":"2020-06-01","y":63129},{"x":"2020-07-01","y":59237},{"x":"2020-08-01","y":56309},{"x":"2020-09-01","y":54993},{"x":"2020-10-01","y":54433},{"x":"2020-11-01","y":53912},{"x":"2020-12-01","y":59125},{"x":"2021-01-01","y":51361},{"x":"2021-02-01","y":51191},{"x":"2021-03-01","y":63080},{"x":"2021-04-01","y":57861},{"x":"2021-05-01","y":58784},{"x":"2021-06-01","y":63041},{"x":"2021-07-01","y":60555},{"x":"2021-08-01","y":59721},{"x":"2021-09-01","y":56150},{"x":"2021-10-01","y":55161},{"x":"2021-11-01","y":58229},{"x":"2021-12-01","y":60806},{"x":"2022-01-01","y":48868},{"x":"2022-02-01","y":50830},{"x":"2022-03-01","y":62977},{"x":"2022-04-01","y":60073},{"x":"2022-05-01","y":65565},{"x":"2022-06-01","y":64251},{"x":"2022-07-01","y":62359},{"x":"2022-08-01","y":65831},{"x":"2022-09-01","y":60619},{"x":"2022-10-01","y":59996},{"x":"2022-11-01","y":60789},{"x":"2022-12-01","y":61223},{"x":"2023-01-01","y":58356},{"x":"2023-02-01","y":0}],"color":"rgba(46,120,210,0.3)"}]}